[
  {
    "id": 1,
    "name": "サルノリ",
    "status": {
      "H": 50,
      "A": 65,
      "B": 50,
      "C": 40,
      "D": 40,
      "S": 65
    },
    "types": {
      "type_1": 4,
      "type_2": null
    }
  },
  {
    "id": 2,
    "name": "バチンキー",
    "status": {
      "H": 70,
      "A": 85,
      "B": 70,
      "C": 55,
      "D": 60,
      "S": 80
    },
    "types": {
      "type_1": 4,
      "type_2": null
    }
  },
  {
    "id": 3,
    "name": "ゴリランダー",
    "status": {
      "H": 100,
      "A": 125,
      "B": 90,
      "C": 60,
      "D": 70,
      "S": 85
    },
    "types": {
      "type_1": 4,
      "type_2": null
    }
  },
  {
    "id": 4,
    "name": "ヒバニー",
    "status": {
      "H": 50,
      "A": 71,
      "B": 40,
      "C": 40,
      "D": 40,
      "S": 69
    },
    "types": {
      "type_1": 1,
      "type_2": null
    }
  },
  {
    "id": 5,
    "name": "ラビフット",
    "status": {
      "H": 65,
      "A": 86,
      "B": 60,
      "C": 55,
      "D": 60,
      "S": 94
    },
    "types": {
      "type_1": 1,
      "type_2": null
    }
  },
  {
    "id": 6,
    "name": "エースバーン",
    "status": {
      "H": 80,
      "A": 116,
      "B": 75,
      "C": 65,
      "D": 75,
      "S": 119
    },
    "types": {
      "type_1": 1,
      "type_2": null
    }
  },
  {
    "id": 7,
    "name": "メッソン",
    "status": {
      "H": 50,
      "A": 40,
      "B": 40,
      "C": 70,
      "D": 40,
      "S": 70
    },
    "types": {
      "type_1": 2,
      "type_2": null
    }
  },
  {
    "id": 8,
    "name": "ジメレオン",
    "status": {
      "H": 65,
      "A": 60,
      "B": 55,
      "C": 95,
      "D": 55,
      "S": 90
    },
    "types": {
      "type_1": 2,
      "type_2": null
    }
  },
  {
    "id": 9,
    "name": "インテレオン",
    "status": {
      "H": 70,
      "A": 85,
      "B": 65,
      "C": 125,
      "D": 65,
      "S": 120
    },
    "types": {
      "type_1": 2,
      "type_2": null
    }
  },
  {
    "id": 10,
    "name": "サッチムシ",
    "status": {
      "H": 25,
      "A": 20,
      "B": 20,
      "C": 25,
      "D": 45,
      "S": 45
    },
    "types": {
      "type_1": 11,
      "type_2": null
    }
  },
  {
    "id": 11,
    "name": "レドームシ",
    "status": {
      "H": 50,
      "A": 35,
      "B": 80,
      "C": 50,
      "D": 90,
      "S": 30
    },
    "types": {
      "type_1": 11,
      "type_2": 10
    }
  },
  {
    "id": 12,
    "name": "イオルブ",
    "status": {
      "H": 60,
      "A": 45,
      "B": 110,
      "C": 80,
      "D": 120,
      "S": 90
    },
    "types": {
      "type_1": 11,
      "type_2": 10
    }
  },
  {
    "id": 13,
    "name": "キャタピー",
    "status": {
      "H": 45,
      "A": 30,
      "B": 35,
      "C": 20,
      "D": 20,
      "S": 45
    },
    "types": {
      "type_1": 11,
      "type_2": null
    }
  },
  {
    "id": 14,
    "name": "トランセル",
    "status": {
      "H": 50,
      "A": 20,
      "B": 55,
      "C": 25,
      "D": 25,
      "S": 30
    },
    "types": {
      "type_1": 11,
      "type_2": null
    }
  },
  {
    "id": 15,
    "name": "バタフリー",
    "status": {
      "H": 60,
      "A": 45,
      "B": 50,
      "C": 90,
      "D": 80,
      "S": 70
    },
    "types": {
      "type_1": 11,
      "type_2": 9
    }
  },
  {
    "id": 16,
    "name": "アゴジムシ",
    "status": {
      "H": 47,
      "A": 62,
      "B": 45,
      "C": 55,
      "D": 45,
      "S": 46
    },
    "types": {
      "type_1": 11,
      "type_2": null
    }
  },
  {
    "id": 17,
    "name": "デンジムシ",
    "status": {
      "H": 57,
      "A": 82,
      "B": 95,
      "C": 55,
      "D": 75,
      "S": 36
    },
    "types": {
      "type_1": 11,
      "type_2": 3
    }
  },
  {
    "id": 18,
    "name": "クワガノン",
    "status": {
      "H": 77,
      "A": 70,
      "B": 90,
      "C": 145,
      "D": 75,
      "S": 43
    },
    "types": {
      "type_1": 11,
      "type_2": 3
    }
  },
  {
    "id": 19,
    "name": "ホーホー",
    "status": {
      "H": 60,
      "A": 30,
      "B": 30,
      "C": 36,
      "D": 56,
      "S": 50
    },
    "types": {
      "type_1": 0,
      "type_2": 9
    }
  },
  {
    "id": 20,
    "name": "ヨルノズク",
    "status": {
      "H": 100,
      "A": 50,
      "B": 50,
      "C": 86,
      "D": 96,
      "S": 70
    },
    "types": {
      "type_1": 0,
      "type_2": 9
    }
  },
  {
    "id": 21,
    "name": "ココガラ",
    "status": {
      "H": 38,
      "A": 47,
      "B": 35,
      "C": 33,
      "D": 35,
      "S": 57
    },
    "types": {
      "type_1": 9,
      "type_2": null
    }
  },
  {
    "id": 22,
    "name": "アオガラス",
    "status": {
      "H": 68,
      "A": 67,
      "B": 55,
      "C": 43,
      "D": 55,
      "S": 77
    },
    "types": {
      "type_1": 9,
      "type_2": null
    }
  },
  {
    "id": 23,
    "name": "アーマーガア",
    "status": {
      "H": 98,
      "A": 87,
      "B": 105,
      "C": 53,
      "D": 85,
      "S": 67
    },
    "types": {
      "type_1": 9,
      "type_2": 16
    }
  },
  {
    "id": 24,
    "name": "ホシガリス",
    "status": {
      "H": 70,
      "A": 55,
      "B": 55,
      "C": 35,
      "D": 35,
      "S": 25
    },
    "types": {
      "type_1": 0,
      "type_2": null
    }
  },
  {
    "id": 25,
    "name": "ヨクバリス",
    "status": {
      "H": 120,
      "A": 95,
      "B": 95,
      "C": 55,
      "D": 75,
      "S": 20
    },
    "types": {
      "type_1": 0,
      "type_2": null
    }
  },
  {
    "id": 26,
    "name": "マメパト",
    "status": {
      "H": 50,
      "A": 55,
      "B": 50,
      "C": 36,
      "D": 30,
      "S": 43
    },
    "types": {
      "type_1": 0,
      "type_2": 9
    }
  },
  {
    "id": 27,
    "name": "ハトーボー",
    "status": {
      "H": 62,
      "A": 77,
      "B": 62,
      "C": 50,
      "D": 42,
      "S": 65
    },
    "types": {
      "type_1": 0,
      "type_2": 9
    }
  },
  {
    "id": 28,
    "name": "ケンホロウ",
    "status": {
      "H": 80,
      "A": 115,
      "B": 80,
      "C": 65,
      "D": 55,
      "S": 93
    },
    "types": {
      "type_1": 0,
      "type_2": 9
    }
  },
  {
    "id": 29,
    "name": "クスネ",
    "status": {
      "H": 40,
      "A": 28,
      "B": 28,
      "C": 47,
      "D": 52,
      "S": 50
    },
    "types": {
      "type_1": 15,
      "type_2": null
    }
  },
  {
    "id": 30,
    "name": "フォクスライ",
    "status": {
      "H": 70,
      "A": 58,
      "B": 58,
      "C": 87,
      "D": 92,
      "S": 90
    },
    "types": {
      "type_1": 15,
      "type_2": null
    }
  },
  {
    "id": 31,
    "name": "ガラルジグザグマ",
    "status": {
      "H": 38,
      "A": 30,
      "B": 41,
      "C": 30,
      "D": 41,
      "S": 60
    },
    "types": {
      "type_1": 15,
      "type_2": 0
    }
  },
  {
    "id": 32,
    "name": "ガラルマッスグマ",
    "status": {
      "H": 78,
      "A": 70,
      "B": 61,
      "C": 50,
      "D": 61,
      "S": 100
    },
    "types": {
      "type_1": 15,
      "type_2": 0
    }
  },
  {
    "id": 33,
    "name": "タチフサグマ",
    "status": {
      "H": 93,
      "A": 90,
      "B": 101,
      "C": 60,
      "D": 81,
      "S": 95
    },
    "types": {
      "type_1": 15,
      "type_2": 0
    }
  },
  {
    "id": 34,
    "name": "ウールー",
    "status": {
      "H": 42,
      "A": 40,
      "B": 55,
      "C": 40,
      "D": 45,
      "S": 48
    },
    "types": {
      "type_1": 0,
      "type_2": null
    }
  },
  {
    "id": 35,
    "name": "バイウールー",
    "status": {
      "H": 72,
      "A": 80,
      "B": 100,
      "C": 60,
      "D": 90,
      "S": 88
    },
    "types": {
      "type_1": 0,
      "type_2": null
    }
  },
  {
    "id": 36,
    "name": "ハスボー",
    "status": {
      "H": 40,
      "A": 30,
      "B": 30,
      "C": 40,
      "D": 50,
      "S": 30
    },
    "types": {
      "type_1": 2,
      "type_2": 4
    }
  },
  {
    "id": 37,
    "name": "ハスブレロ",
    "status": {
      "H": 60,
      "A": 50,
      "B": 50,
      "C": 60,
      "D": 70,
      "S": 50
    },
    "types": {
      "type_1": 2,
      "type_2": 4
    }
  },
  {
    "id": 38,
    "name": "ルンパッパ",
    "status": {
      "H": 80,
      "A": 70,
      "B": 70,
      "C": 90,
      "D": 100,
      "S": 70
    },
    "types": {
      "type_1": 2,
      "type_2": 4
    }
  },
  {
    "id": 39,
    "name": "タネボー",
    "status": {
      "H": 40,
      "A": 40,
      "B": 50,
      "C": 30,
      "D": 30,
      "S": 30
    },
    "types": {
      "type_1": 4,
      "type_2": null
    }
  },
  {
    "id": 40,
    "name": "コノハナ",
    "status": {
      "H": 70,
      "A": 70,
      "B": 40,
      "C": 60,
      "D": 40,
      "S": 60
    },
    "types": {
      "type_1": 4,
      "type_2": 15
    }
  },
  {
    "id": 41,
    "name": "ダーテング",
    "status": {
      "H": 90,
      "A": 100,
      "B": 60,
      "C": 90,
      "D": 60,
      "S": 80
    },
    "types": {
      "type_1": 4,
      "type_2": 15
    }
  },
  {
    "id": 42,
    "name": "カムカメ",
    "status": {
      "H": 50,
      "A": 64,
      "B": 50,
      "C": 38,
      "D": 38,
      "S": 44
    },
    "types": {
      "type_1": 2,
      "type_2": null
    }
  },
  {
    "id": 43,
    "name": "カジリガメ",
    "status": {
      "H": 90,
      "A": 115,
      "B": 90,
      "C": 48,
      "D": 68,
      "S": 74
    },
    "types": {
      "type_1": 2,
      "type_2": null
    }
  },
  {
    "id": 44,
    "name": "チョロネコ",
    "status": {
      "H": 41,
      "A": 50,
      "B": 37,
      "C": 50,
      "D": 37,
      "S": 66
    },
    "types": {
      "type_1": 15,
      "type_2": null
    }
  },
  {
    "id": 45,
    "name": "レパルダス",
    "status": {
      "H": 64,
      "A": 88,
      "B": 50,
      "C": 88,
      "D": 50,
      "S": 106
    },
    "types": {
      "type_1": 15,
      "type_2": null
    }
  },
  {
    "id": 46,
    "name": "ワンパチ",
    "status": {
      "H": 59,
      "A": 45,
      "B": 50,
      "C": 40,
      "D": 50,
      "S": 26
    },
    "types": {
      "type_1": 3,
      "type_2": null
    }
  },
  {
    "id": 47,
    "name": "パルスワン",
    "status": {
      "H": 69,
      "A": 90,
      "B": 60,
      "C": 90,
      "D": 60,
      "S": 121
    },
    "types": {
      "type_1": 3,
      "type_2": null
    }
  },
  {
    "id": 48,
    "name": "ホルビー",
    "status": {
      "H": 38,
      "A": 36,
      "B": 38,
      "C": 32,
      "D": 36,
      "S": 57
    },
    "types": {
      "type_1": 0,
      "type_2": null
    }
  },
  {
    "id": 49,
    "name": "ホルード",
    "status": {
      "H": 85,
      "A": 56,
      "B": 77,
      "C": 50,
      "D": 77,
      "S": 78
    },
    "types": {
      "type_1": 0,
      "type_2": 8
    }
  },
  {
    "id": 50,
    "name": "チラーミィ",
    "status": {
      "H": 55,
      "A": 50,
      "B": 40,
      "C": 40,
      "D": 40,
      "S": 75
    },
    "types": {
      "type_1": 0,
      "type_2": null
    }
  },
  {
    "id": 51,
    "name": "チラチーノ",
    "status": {
      "H": 75,
      "A": 95,
      "B": 60,
      "C": 65,
      "D": 60,
      "S": 115
    },
    "types": {
      "type_1": 0,
      "type_2": null
    }
  },
  {
    "id": 52,
    "name": "アマカジ",
    "status": {
      "H": 42,
      "A": 30,
      "B": 38,
      "C": 30,
      "D": 38,
      "S": 32
    },
    "types": {
      "type_1": 4,
      "type_2": null
    }
  },
  {
    "id": 53,
    "name": "アママイコ",
    "status": {
      "H": 52,
      "A": 40,
      "B": 48,
      "C": 40,
      "D": 48,
      "S": 62
    },
    "types": {
      "type_1": 4,
      "type_2": null
    }
  },
  {
    "id": 54,
    "name": "アマージョ",
    "status": {
      "H": 72,
      "A": 120,
      "B": 98,
      "C": 50,
      "D": 98,
      "S": 72
    },
    "types": {
      "type_1": 4,
      "type_2": null
    }
  },
  {
    "id": 55,
    "name": "ナゾノクサ",
    "status": {
      "H": 45,
      "A": 50,
      "B": 55,
      "C": 75,
      "D": 65,
      "S": 30
    },
    "types": {
      "type_1": 4,
      "type_2": 7
    }
  },
  {
    "id": 56,
    "name": "クサイハナ",
    "status": {
      "H": 60,
      "A": 65,
      "B": 70,
      "C": 85,
      "D": 75,
      "S": 40
    },
    "types": {
      "type_1": 4,
      "type_2": 7
    }
  },
  {
    "id": 57,
    "name": "ラフレシア",
    "status": {
      "H": 75,
      "A": 80,
      "B": 85,
      "C": 110,
      "D": 90,
      "S": 50
    },
    "types": {
      "type_1": 4,
      "type_2": 7
    }
  },
  {
    "id": 58,
    "name": "キレイハナ",
    "status": {
      "H": 75,
      "A": 80,
      "B": 95,
      "C": 90,
      "D": 100,
      "S": 50
    },
    "types": {
      "type_1": 4,
      "type_2": null
    }
  },
  {
    "id": 59,
    "name": "スボミー",
    "status": {
      "H": 40,
      "A": 30,
      "B": 35,
      "C": 50,
      "D": 70,
      "S": 55
    },
    "types": {
      "type_1": 4,
      "type_2": 7
    }
  },
  {
    "id": 60,
    "name": "ロゼリア",
    "status": {
      "H": 50,
      "A": 60,
      "B": 45,
      "C": 100,
      "D": 80,
      "S": 65
    },
    "types": {
      "type_1": 4,
      "type_2": 7
    }
  },
  {
    "id": 61,
    "name": "ロズレイド",
    "status": {
      "H": 60,
      "A": 70,
      "B": 65,
      "C": 125,
      "D": 105,
      "S": 90
    },
    "types": {
      "type_1": 4,
      "type_2": 7
    }
  },
  {
    "id": 62,
    "name": "キャモメ",
    "status": {
      "H": 40,
      "A": 30,
      "B": 30,
      "C": 55,
      "D": 30,
      "S": 85
    },
    "types": {
      "type_1": 2,
      "type_2": 9
    }
  },
  {
    "id": 63,
    "name": "ぺリッパー",
    "status": {
      "H": 60,
      "A": 50,
      "B": 100,
      "C": 95,
      "D": 70,
      "S": 65
    },
    "types": {
      "type_1": 2,
      "type_2": 9
    }
  },
  {
    "id": 64,
    "name": "バチュル",
    "status": {
      "H": 50,
      "A": 47,
      "B": 50,
      "C": 57,
      "D": 50,
      "S": 65
    },
    "types": {
      "type_1": 11,
      "type_2": 3
    }
  },
  {
    "id": 65,
    "name": "デンチュラ",
    "status": {
      "H": 70,
      "A": 77,
      "B": 60,
      "C": 97,
      "D": 60,
      "S": 108
    },
    "types": {
      "type_1": 11,
      "type_2": 3
    }
  },
  {
    "id": 66,
    "name": "ラクライ",
    "status": {
      "H": 40,
      "A": 45,
      "B": 40,
      "C": 65,
      "D": 40,
      "S": 65
    },
    "types": {
      "type_1": 3,
      "type_2": null
    }
  },
  {
    "id": 67,
    "name": "ライボルト",
    "status": {
      "H": 70,
      "A": 75,
      "B": 60,
      "C": 105,
      "D": 60,
      "S": 105
    },
    "types": {
      "type_1": 3,
      "type_2": null
    }
  },
  {
    "id": 68,
    "name": "ロコン",
    "status": {
      "H": 38,
      "A": 41,
      "B": 40,
      "C": 50,
      "D": 65,
      "S": 65
    },
    "types": {
      "type_1": 1,
      "type_2": null
    }
  },
  {
    "id": 69,
    "name": "キュウコン",
    "status": {
      "H": 73,
      "A": 76,
      "B": 75,
      "C": 81,
      "D": 100,
      "S": 100
    },
    "types": {
      "type_1": 1,
      "type_2": null
    }
  },
  {
    "id": 70,
    "name": "ガーディ",
    "status": {
      "H": 55,
      "A": 70,
      "B": 45,
      "C": 70,
      "D": 50,
      "S": 60
    },
    "types": {
      "type_1": 1,
      "type_2": null
    }
  },
  {
    "id": 71,
    "name": "ウインディ",
    "status": {
      "H": 90,
      "A": 110,
      "B": 80,
      "C": 100,
      "D": 80,
      "S": 95
    },
    "types": {
      "type_1": 1,
      "type_2": null
    }
  },
  {
    "id": 72,
    "name": "バニプッチ",
    "status": {
      "H": 36,
      "A": 50,
      "B": 50,
      "C": 65,
      "D": 60,
      "S": 44
    },
    "types": {
      "type_1": 5,
      "type_2": null
    }
  },
  {
    "id": 73,
    "name": "バニリッチ",
    "status": {
      "H": 51,
      "A": 65,
      "B": 65,
      "C": 80,
      "D": 75,
      "S": 59
    },
    "types": {
      "type_1": 5,
      "type_2": null
    }
  },
  {
    "id": 74,
    "name": "バイバニラ",
    "status": {
      "H": 71,
      "A": 95,
      "B": 85,
      "C": 110,
      "D": 95,
      "S": 79
    },
    "types": {
      "type_1": 5,
      "type_2": null
    }
  },
  {
    "id": 75,
    "name": "ウリムー",
    "status": {
      "H": 50,
      "A": 50,
      "B": 40,
      "C": 30,
      "D": 30,
      "S": 50
    },
    "types": {
      "type_1": 5,
      "type_2": 8
    }
  },
  {
    "id": 76,
    "name": "イノムー",
    "status": {
      "H": 100,
      "A": 100,
      "B": 80,
      "C": 60,
      "D": 60,
      "S": 50
    },
    "types": {
      "type_1": 5,
      "type_2": 8
    }
  },
  {
    "id": 77,
    "name": "マンムー",
    "status": {
      "H": 110,
      "A": 130,
      "B": 80,
      "C": 70,
      "D": 60,
      "S": 80
    },
    "types": {
      "type_1": 5,
      "type_2": 8
    }
  },
  {
    "id": 78,
    "name": "デリバード",
    "status": {
      "H": 45,
      "A": 55,
      "B": 45,
      "C": 65,
      "D": 45,
      "S": 75
    },
    "types": {
      "type_1": 5,
      "type_2": 9
    }
  },
  {
    "id": 79,
    "name": "ユキワラシ",
    "status": {
      "H": 50,
      "A": 50,
      "B": 50,
      "C": 50,
      "D": 50,
      "S": 50
    },
    "types": {
      "type_1": 5,
      "type_2": null
    }
  },
  {
    "id": 80,
    "name": "オニゴーリ",
    "status": {
      "H": 80,
      "A": 80,
      "B": 80,
      "C": 80,
      "D": 80,
      "S": 80
    },
    "types": {
      "type_1": 5,
      "type_2": null
    }
  },
  {
    "id": 81,
    "name": "ユキメノコ",
    "status": {
      "H": 70,
      "A": 80,
      "B": 70,
      "C": 80,
      "D": 70,
      "S": 110
    },
    "types": {
      "type_1": 5,
      "type_2": 13
    }
  },
  {
    "id": 82,
    "name": "ヤジロン",
    "status": {
      "H": 40,
      "A": 40,
      "B": 55,
      "C": 40,
      "D": 70,
      "S": 55
    },
    "types": {
      "type_1": 8,
      "type_2": 10
    }
  },
  {
    "id": 83,
    "name": "ネンドール",
    "status": {
      "H": 60,
      "A": 70,
      "B": 105,
      "C": 70,
      "D": 120,
      "S": 75
    },
    "types": {
      "type_1": 8,
      "type_2": 10
    }
  },
  {
    "id": 84,
    "name": "ドロバンコ",
    "status": {
      "H": 70,
      "A": 100,
      "B": 70,
      "C": 45,
      "D": 55,
      "S": 45
    },
    "types": {
      "type_1": 8,
      "type_2": null
    }
  },
  {
    "id": 85,
    "name": "バンバドロ",
    "status": {
      "H": 100,
      "A": 125,
      "B": 100,
      "C": 55,
      "D": 85,
      "S": 35
    },
    "types": {
      "type_1": 8,
      "type_2": null
    }
  },
  {
    "id": 86,
    "name": "イシズマイ",
    "status": {
      "H": 50,
      "A": 65,
      "B": 85,
      "C": 35,
      "D": 35,
      "S": 55
    },
    "types": {
      "type_1": 11,
      "type_2": 12
    }
  },
  {
    "id": 87,
    "name": "イワパレス",
    "status": {
      "H": 70,
      "A": 105,
      "B": 125,
      "C": 65,
      "D": 75,
      "S": 45
    },
    "types": {
      "type_1": 11,
      "type_2": 12
    }
  },
  {
    "id": 88,
    "name": "ゴビット",
    "status": {
      "H": 59,
      "A": 74,
      "B": 50,
      "C": 35,
      "D": 50,
      "S": 35
    },
    "types": {
      "type_1": 8,
      "type_2": 13
    }
  },
  {
    "id": 89,
    "name": "ゴルーグ",
    "status": {
      "H": 89,
      "A": 124,
      "B": 80,
      "C": 55,
      "D": 80,
      "S": 55
    },
    "types": {
      "type_1": 8,
      "type_2": 13
    }
  },
  {
    "id": 90,
    "name": "ムンナ",
    "status": {
      "H": 76,
      "A": 25,
      "B": 45,
      "C": 67,
      "D": 55,
      "S": 24
    },
    "types": {
      "type_1": 10,
      "type_2": null
    }
  },
  {
    "id": 91,
    "name": "ムシャーナ",
    "status": {
      "H": 116,
      "A": 55,
      "B": 85,
      "C": 107,
      "D": 95,
      "S": 29
    },
    "types": {
      "type_1": 10,
      "type_2": null
    }
  },
  {
    "id": 92,
    "name": "ネイティ",
    "status": {
      "H": 40,
      "A": 50,
      "B": 45,
      "C": 70,
      "D": 45,
      "S": 70
    },
    "types": {
      "type_1": 10,
      "type_2": 9
    }
  },
  {
    "id": 93,
    "name": "ネイティオ",
    "status": {
      "H": 65,
      "A": 75,
      "B": 70,
      "C": 95,
      "D": 70,
      "S": 95
    },
    "types": {
      "type_1": 10,
      "type_2": 9
    }
  },
  {
    "id": 94,
    "name": "ヌイコグマ",
    "status": {
      "H": 70,
      "A": 75,
      "B": 50,
      "C": 45,
      "D": 50,
      "S": 50
    },
    "types": {
      "type_1": 0,
      "type_2": 6
    }
  },
  {
    "id": 95,
    "name": "キテルグマ",
    "status": {
      "H": 120,
      "A": 125,
      "B": 80,
      "C": 55,
      "D": 60,
      "S": 60
    },
    "types": {
      "type_1": 0,
      "type_2": 6
    }
  },
  {
    "id": 96,
    "name": "ユキカブリ",
    "status": {
      "H": 60,
      "A": 62,
      "B": 50,
      "C": 62,
      "D": 60,
      "S": 40
    },
    "types": {
      "type_1": 4,
      "type_2": 5
    }
  },
  {
    "id": 97,
    "name": "ユキノオー",
    "status": {
      "H": 90,
      "A": 92,
      "B": 75,
      "C": 92,
      "D": 85,
      "S": 60
    },
    "types": {
      "type_1": 4,
      "type_2": 5
    }
  },
  {
    "id": 98,
    "name": "クラブ",
    "status": {
      "H": 30,
      "A": 105,
      "B": 90,
      "C": 25,
      "D": 25,
      "S": 50
    },
    "types": {
      "type_1": 2,
      "type_2": null
    }
  },
  {
    "id": 99,
    "name": "キングラー",
    "status": {
      "H": 55,
      "A": 130,
      "B": 115,
      "C": 50,
      "D": 50,
      "S": 75
    },
    "types": {
      "type_1": 2,
      "type_2": null
    }
  },
  {
    "id": 100,
    "name": "ウパー",
    "status": {
      "H": 55,
      "A": 45,
      "B": 45,
      "C": 25,
      "D": 25,
      "S": 15
    },
    "types": {
      "type_1": 2,
      "type_2": 8
    }
  }
]
